carbonpy/__init__.py
carbonpy/error.py
carbonpy/namer.py
carbonpy/version.py
carbonpy-0.52.dist-info/LICENSE
carbonpy-0.52.dist-info/METADATA
carbonpy-0.52.dist-info/WHEEL
carbonpy-0.52.dist-info/top_level.txt
carbonpy-0.52.dist-info/RECORD
