Metadata-Version: 2.1
Name: carbonpy
Version: 0.52
Summary: A Python package which gives IUPAC names of chemical compounds, classifies them and more.
Home-page: https://github.com/harshil21/carbonpy
Author: Harshil Mehta
Author-email: ilovebhagwan@gmail.com
License: UNKNOWN
Platform: UNKNOWN
Classifier: Development Status :: 1 - Planning
Classifier: Intended Audience :: Science/Research
Classifier: Intended Audience :: Education
Classifier: License :: OSI Approved :: Apache Software License
Classifier: Operating System :: OS Independent
Classifier: Programming Language :: Python :: 3
Classifier: Topic :: Scientific/Engineering :: Chemistry
Requires-Python: >=3.5
